[
    {
        "name": "Thiago 1",
        "age": 30,
        "phone": "+55 22 99778-8963",
        "birthday": "1975-12-25",
        "avatar": "https://img2.gratispng.com/20180626/fhs/kisspng-avatar-user-computer-icons-software-developer-5b327cc98b5780.5684824215300354015708.jpg",
        "enable": true,
        "description": "É um fato conhecido de todos que um leitor se distrairá com o conteúdo de texto legível de uma página quando estiver examinando sua diagramação."
    },
    {
        "name": "Isaque 2",
        "age": 33,
        "phone": "+55 22 99778-8963",
        "birthday": "1975-12-25",
        "avatar": "https://img2.gratispng.com/20180626/fhs/kisspng-avatar-user-computer-icons-software-developer-5b327cc98b5780.5684824215300354015708.jpg",
        "enable": true,
        "description": "É um fato conhecido de todos que um leitor se distrairá com o conteúdo de texto legível de uma página quando estiver examinando sua diagramação."
    },
    {
        "name": "Leonardo 3",
        "age": 37,
        "phone": "+55 22 99778-8963",
        "birthday": "1975-12-25",
        "avatar": "https://img2.gratispng.com/20180626/fhs/kisspng-avatar-user-computer-icons-software-developer-5b327cc98b5780.5684824215300354015708.jpg",
        "enable": true,
        "description": "É um fato conhecido de todos que um leitor se distrairá com o conteúdo de texto legível de uma página quando estiver examinando sua diagramação."
    },
    {
        "name": "Neto 4",
        "age": 37,
        "phone": "+55 22 99778-8963",
        "birthday": "1975-12-25",
        "avatar": "https://img2.gratispng.com/20180626/fhs/kisspng-avatar-user-computer-icons-software-developer-5b327cc98b5780.5684824215300354015708.jpg",
        "enable": true,
        "description": "É um fato conhecido de todos que um leitor se distrairá com o conteúdo de texto legível de uma página quando estiver examinando sua diagramação."
    },
    {
        "name": "Cintia 5",
        "age": 37,
        "phone": "+55 22 99778-8963",
        "birthday": "1975-12-25",
        "avatar": "https://img2.gratispng.com/20180626/fhs/kisspng-avatar-user-computer-icons-software-developer-5b327cc98b5780.5684824215300354015708.jpg",
        "enable": true,
        "description": "É um fato conhecido de todos que um leitor se distrairá com o conteúdo de texto legível de uma página quando estiver examinando sua diagramação."
    },
    {
        "name": "Marcos 6",
        "age": 37,
        "phone": "+55 22 99778-8963",
        "birthday": "1975-12-25",
        "avatar": "https://img2.gratispng.com/20180626/fhs/kisspng-avatar-user-computer-icons-software-developer-5b327cc98b5780.5684824215300354015708.jpg",
        "enable": true,
        "description": "É um fato conhecido de todos que um leitor se distrairá com o conteúdo de texto legível de uma página quando estiver examinando sua diagramação."
    },
    {
        "name": "Carlos 7",
        "age": 37,
        "phone": "+55 22 99778-8963",
        "birthday": "1975-12-25",
        "avatar": "https://img2.gratispng.com/20180626/fhs/kisspng-avatar-user-computer-icons-software-developer-5b327cc98b5780.5684824215300354015708.jpg",
        "enable": true,
        "description": "É um fato conhecido de todos que um leitor se distrairá com o conteúdo de texto legível de uma página quando estiver examinando sua diagramação."
    },
    {
        "name": "Carlos 8",
        "age": 37,
        "phone": "+55 22 99778-8963",
        "birthday": "1975-12-25",
        "avatar": "https://img2.gratispng.com/20180626/fhs/kisspng-avatar-user-computer-icons-software-developer-5b327cc98b5780.5684824215300354015708.jpg",
        "enable": true,
        "description": "É um fato conhecido de todos que um leitor se distrairá com o conteúdo de texto legível de uma página quando estiver examinando sua diagramação."
    },
    {
        "name": "Carlos 9",
        "age": 37,
        "phone": "+55 22 99778-8963",
        "birthday": "1975-12-25",
        "avatar": "https://img2.gratispng.com/20180626/fhs/kisspng-avatar-user-computer-icons-software-developer-5b327cc98b5780.5684824215300354015708.jpg",
        "enable": true,
        "description": "É um fato conhecido de todos que um leitor se distrairá com o conteúdo de texto legível de uma página quando estiver examinando sua diagramação."
    },
    {
        "name": "Carlos 10",
        "age": 37,
        "phone": "+55 22 99778-8963",
        "birthday": "1975-12-25",
        "avatar": "https://img2.gratispng.com/20180626/fhs/kisspng-avatar-user-computer-icons-software-developer-5b327cc98b5780.5684824215300354015708.jpg",
        "enable": true,
        "description": "É um fato conhecido de todos que um leitor se distrairá com o conteúdo de texto legível de uma página quando estiver examinando sua diagramação."
    },
    {
        "name": "Carlos 11",
        "age": 37,
        "phone": "+55 22 99778-8963",
        "birthday": "1975-12-25",
        "avatar": "https://img2.gratispng.com/20180626/fhs/kisspng-avatar-user-computer-icons-software-developer-5b327cc98b5780.5684824215300354015708.jpg",
        "enable": true,
        "description": "É um fato conhecido de todos que um leitor se distrairá com o conteúdo de texto legível de uma página quando estiver examinando sua diagramação."
    },
    {
        "name": "Carlos 12",
        "age": 37,
        "phone": "+55 22 99778-8963",
        "birthday": "1975-12-25",
        "avatar": "https://img2.gratispng.com/20180626/fhs/kisspng-avatar-user-computer-icons-software-developer-5b327cc98b5780.5684824215300354015708.jpg",
        "enable": true,
        "description": "É um fato conhecido de todos que um leitor se distrairá com o conteúdo de texto legível de uma página quando estiver examinando sua diagramação."
    }
]

    
